sheetless/__init__.py
sheetless/cli.py
sheetless/convert.py
sheetless/utils.py
sheetless-0.1.2.dist-info/licenses/LICENSE.txt
sheetless-0.1.2.dist-info/METADATA
sheetless-0.1.2.dist-info/WHEEL
sheetless-0.1.2.dist-info/entry_points.txt
sheetless-0.1.2.dist-info/top_level.txt
sheetless-0.1.2.dist-info/RECORD
