Metadata-Version: 2.4
Name: sheetless
Version: 0.1.2
Summary: CLI tool to convert Excel and CSV files to DuckDB
Home-page: https://github.com/georgoulis/sheetless/
Author: georgoulis
Author-email: georgoulis.christos.c@gmail.com
License: MIT
Project-URL: Source, https://github.com/georgoulis/sheetless/
Platform: any
Classifier: Development Status :: 3 - Alpha
Classifier: Programming Language :: Python
License-File: LICENSE.txt
Requires-Dist: importlib-metadata; python_version < "3.8"
Requires-Dist: click>=8.1.8
Requires-Dist: duckdb>=1.2.2
Requires-Dist: pandas>=2.2.3
Requires-Dist: openpyxl>=3.1.5
Provides-Extra: testing
Requires-Dist: setuptools; extra == "testing"
Requires-Dist: pytest; extra == "testing"
Requires-Dist: pytest-cov; extra == "testing"
Requires-Dist: flake8; extra == "testing"
Requires-Dist: black; extra == "testing"
Provides-Extra: dev
Requires-Dist: setuptools-scm; extra == "dev"
Requires-Dist: build; extra == "dev"
Requires-Dist: twine; extra == "dev"
Requires-Dist: wheel; extra == "dev"
Requires-Dist: setuptools; extra == "dev"
Dynamic: license-file
